socotratools/__init__.py
socotratools/client.py
socotratools/dates.py
socotratools-1.3.15.dist-info/METADATA
socotratools-1.3.15.dist-info/WHEEL
socotratools-1.3.15.dist-info/top_level.txt
socotratools-1.3.15.dist-info/RECORD
