Metadata-Version: 2.1
Name: socotratools
Version: 1.3.15
Summary: Socotra Tools
Home-page: https://www.socotra.com
Maintainer: Dinesh Shenoy
Maintainer-email: dinesh.shenoy@socotra.com
License: all rights reserved
Platform: UNKNOWN
Requires-Dist: requests (==2.22.0)
